meshadmin/__init__.py
meshadmin/cli/__init__.py
meshadmin/cli/config.py
meshadmin/cli/main.py
meshadmin/cli/utils.py
meshadmin/cli/commands/__init__.py
meshadmin/cli/commands/context.py
meshadmin/cli/commands/host.py
meshadmin/cli/commands/nebula.py
meshadmin/cli/commands/network.py
meshadmin/cli/commands/service.py
meshadmin/cli/commands/system.py
meshadmin/cli/commands/template.py
meshadmin/cli/tests/__init__.py
meshadmin/cli/tests/conftest.py
meshadmin/cli/tests/test_context.py
meshadmin/cli/tests/test_host.py
meshadmin/cli/tests/test_integration.py
meshadmin/cli/tests/test_network.py
meshadmin/cli/tests/test_template.py
meshadmin/common/schemas.py
meshadmin/common/utils.py
meshadmin/server/manage.py
meshadmin/server/tailwind.config.js
meshadmin/server/assets/__init__.py
meshadmin/server/assets/config.yml
meshadmin/server/assets/Darwin/arm64/nebula
meshadmin/server/assets/Darwin/arm64/nebula-cert
meshadmin/server/assets/Linux/aarch64/nebula
meshadmin/server/assets/Linux/aarch64/nebula-cert
meshadmin/server/assets/Linux/x86_64/nebula
meshadmin/server/assets/Linux/x86_64/nebula-cert
meshadmin/server/networks/__init__.py
meshadmin/server/networks/admin.py
meshadmin/server/networks/api.py
meshadmin/server/networks/apps.py
meshadmin/server/networks/forms.py
meshadmin/server/networks/mixins.py
meshadmin/server/networks/models.py
meshadmin/server/networks/services.py
meshadmin/server/networks/urls.py
meshadmin/server/networks/__snapshots__/tests.ambr
meshadmin/server/networks/migrations/0001_initial.py
meshadmin/server/networks/migrations/0002_firewall_rule.py
meshadmin/server/networks/migrations/0003_alter_host_assigned_ip.py
meshadmin/server/networks/migrations/0004_alter_host_unique_together.py
meshadmin/server/networks/migrations/0005_host_firewall.py
meshadmin/server/networks/migrations/0006_alter_host_firewall.py
meshadmin/server/networks/migrations/0007_rename_firewall_host_firewalls.py
meshadmin/server/networks/migrations/0008_host_last_config_refresh.py
meshadmin-1.2.0.dist-info/METADATA
meshadmin-1.2.0.dist-info/WHEEL
meshadmin-1.2.0.dist-info/entry_points.txt
meshadmin-1.2.0.dist-info/RECORD
