Metadata-Version: 2.4
Name: meshadmin
Version: 1.2.0
Summary: Management for Nebula Mesh networks.
License: Proprietary
Requires-Python: >=3.13
Requires-Dist: httpx>=0.28.1
Requires-Dist: jwcrypto>=1.5.6
Requires-Dist: pydantic>=2.10.6
Requires-Dist: pyjwt>=2.10.1
Requires-Dist: pyyaml>=6.0.2
Requires-Dist: rich>=13.9.4
Requires-Dist: structlog>=25.2.0
Requires-Dist: typer>=0.15.2
Provides-Extra: server
Requires-Dist: django-allauth[socialaccount]>=65.4.1; extra == 'server'
Requires-Dist: django-cotton>=1.6.0; extra == 'server'
Requires-Dist: django-htmx>=1.22.0; extra == 'server'
Requires-Dist: django-ninja>=1.3.0; extra == 'server'
Requires-Dist: django-structlog>=9.0.1; extra == 'server'
Requires-Dist: django-tailwind-cli==2.20.1; extra == 'server'
Requires-Dist: django-tailwind>=3.8.0; extra == 'server'
Requires-Dist: django>=5.2.1; extra == 'server'
Requires-Dist: jinja2>=3.1.6; extra == 'server'
Requires-Dist: python-dotenv>=1.1.0; extra == 'server'
Requires-Dist: python-semantic-release>=9.20.0; extra == 'server'
Requires-Dist: syrupy>=4.8.2; extra == 'server'
Requires-Dist: uvicorn>=0.34.0; extra == 'server'
Requires-Dist: whitenoise>=6.9.0; extra == 'server'
